Metadata-Version: 2.4
Name: passagemath-gurobi
Version: 10.4.1
Summary: Gurobi backend for Sage MixedIntegerLinearProgram
Home-page: https://github.com/passagemath/passagemath-gurobi
Author: Nathann Cohen, Martin Albrecht, Matthias Koeppe, John Perry, David Coudert, Jori Mäntysalo, Jeroen Demeyer, Erik M. Bray, Emil R. Vaughan, and others
Author-email: mkoeppe@math.ucdavis.edu
License: GPLv2+
Keywords: milp,linear-programming,optimization
Classifier: Development Status :: 5 - Production/Stable
Classifier: Intended Audience :: Science/Research
Classifier: License :: OSI Approved :: GNU General Public License v2 or later (GPLv2+)
Classifier: Programming Language :: Python
Classifier: Programming Language :: Python :: 3
Classifier: Programming Language :: Python :: 3.6
Classifier: Programming Language :: Python :: 3.7
Classifier: Programming Language :: Python :: 3.8
Classifier: Programming Language :: Python :: 3.9
Classifier: Programming Language :: Python :: 3.10
Classifier: Programming Language :: Python :: 3.11
Classifier: Programming Language :: Python :: 3.12
Classifier: Programming Language :: Python :: 3.13
License-File: LICENSE
Requires-Dist: passagemath-categories
Provides-Extra: doc
Requires-Dist: sphinx; extra == "doc"
Dynamic: author
Dynamic: author-email
Dynamic: classifier
Dynamic: description
Dynamic: description-content-type
Dynamic: home-page
Dynamic: keywords
Dynamic: license
Dynamic: license-file
Dynamic: provides-extra
Dynamic: requires-dist
Dynamic: summary
